redjlog/__init__.py
redjlog/helper.py
redjlog/exception/Exception.py
redjlog/exception/ExceptionHandler.py
redjlog/exception/HttpException.py
redjlog/exception/KnoxException.py
redjlog/exception/__init__.py
redjlog/management/__init__.py
redjlog/management/server.py
redjlog/management/setting.py
redjlog/middleware/RequestLog.py
redjlog/middleware/__init__.py
Redj_LogServer-0.2.6.dist-info/LICENSE
Redj_LogServer-0.2.6.dist-info/METADATA
Redj_LogServer-0.2.6.dist-info/WHEEL
Redj_LogServer-0.2.6.dist-info/top_level.txt
Redj_LogServer-0.2.6.dist-info/RECORD
